Metadata-Version: 1.2
Name: webdebug
Version: 1.1.0
Summary: Webdebug
Home-page: https://github.com/fpim/webdebug
Author: Louis@FPIM
Author-email: frompythonimportme@gmail.com
License: MIT
Platform: UNKNOWN
Classifier: Programming Language :: Python :: 3
Classifier: License :: OSI Approved :: MIT License
Classifier: Operating System :: OS Independent
Requires-Python: >=3.4
